wable/__init__.py
wable/client.py
wable-0.0.5.dist-info/LICENSE.txt
wable-0.0.5.dist-info/WHEEL
wable-0.0.5.dist-info/METADATA
wable-0.0.5.dist-info/RECORD
