Metadata-Version: 2.1
Name: wable
Version: 0.0.5
Summary: A client to communicate with wable.org api
Home-page: https://wable.org
License: Apache-2.0
Keywords: wable,service,client
Author: Madhu
Author-email: madhu@wable.org
Maintainer: Madhu
Maintainer-email: madhu@wable.org
Requires-Python: >3.6
Classifier: Development Status :: 2 - Pre-Alpha
Classifier: Intended Audience :: Developers
Classifier: License :: OSI Approved :: Apache Software License
Classifier: Programming Language :: Python :: 3
Classifier: Programming Language :: Python :: 3.7
Classifier: Programming Language :: Python :: 3.8
Classifier: Programming Language :: Python :: 3.9
Classifier: Topic :: Internet :: WWW/HTTP
Requires-Dist: requests (>=2.25.1,<3.0.0)
Project-URL: Repository, https://gitlab.com/wable/wable-client
